pyavaspec/__init__.py
pyavaspec/avacli.py
pyavaspec/pyavaspec.py
pyavaspec_tspspi-1.0.2a2.dist-info/LICENSE.md
pyavaspec_tspspi-1.0.2a2.dist-info/METADATA
pyavaspec_tspspi-1.0.2a2.dist-info/WHEEL
pyavaspec_tspspi-1.0.2a2.dist-info/entry_points.txt
pyavaspec_tspspi-1.0.2a2.dist-info/top_level.txt
pyavaspec_tspspi-1.0.2a2.dist-info/RECORD
