Metadata-Version: 2.1
Name: pyavaspec-tspspi
Version: 1.0.2a2
Summary: Unofficial library and tool to communicate with AvaSpec-2048-2 spectrometer
Home-page: https://github.com/tspspi/pyavaspec
Author: Thomas Spielauer
Author-email: pypipackages01@tspi.at
Classifier: Programming Language :: Python :: 3
Classifier: License :: OSI Approved :: BSD License
Classifier: Operating System :: OS Independent
Requires-Python: >=3.8
License-File: LICENSE.md
Requires-Dist: sdg1032x-tspspi (>=0.0.1a1)
Requires-Dist: pyusb (>=1.0.2)
Requires-Dist: matplotlib (>=3.4.1)
